coalitions/__init__.py
coalitions/coalitionalgame.py
coalitions/typedcoalitionalgame.py
coalitions/util.py
coalitions-0.4.0.dist-info/METADATA
coalitions-0.4.0.dist-info/WHEEL
coalitions-0.4.0.dist-info/licenses/LICENSE
coalitions-0.4.0.dist-info/RECORD
