Metadata-Version: 2.1
Name: coalitions
Version: 0.4.0
Summary: Utilities for Coalitional Games
Project-URL: Homepage, https://github.com/gmweinberg/coalitions
Project-URL: Issues, https://github.com/gmweinberg/coalitions/issues
Author-email: George Weinberg <gmweinberg@fastmail.fm>
License: MIT License
License-File: LICENSE
Keywords: banzhaf,coalitional games,game theory,shapley
Classifier: License :: OSI Approved :: MIT License
Classifier: Operating System :: OS Independent
Classifier: Programming Language :: Python :: 3
Requires-Python: >=3.8
